LICENSE
MANIFEST.in
README.rst
setup.py
desktop_security_assistant/__init__.py
desktop_security_assistant/main.py
desktop_security_assistant/ui.py
desktop_security_assistant/utils.py
desktop_security_assistant.egg-info/PKG-INFO
desktop_security_assistant.egg-info/SOURCES.txt
desktop_security_assistant.egg-info/dependency_links.txt
desktop_security_assistant.egg-info/entry_points.txt
desktop_security_assistant.egg-info/not-zip-safe
desktop_security_assistant.egg-info/requires.txt
desktop_security_assistant.egg-info/top_level.txt
desktop_security_assistant/checks/general.yaml
desktop_security_assistant/data/icon.png
desktop_security_assistant/data/rating.png
desktop_security_assistant/data/security-assistant.ui